onetick/README.query_webapi.md
onetick/license.query_webapi.txt
onetick/eps_generator_webapi/__main__.py
onetick/eps_generator_webapi/eps_generator.py
onetick/eps_generator_webapi/eps_list.otq
onetick/eps_generator_webapi/eps_list_doc.otq
onetick/eps_generator_webapi/plugin.py
onetick/eps_generator_webapi/utils.py
onetick/query_webapi/__init__.py
onetick/query_webapi/_eps_factory.py
onetick/query_webapi/_internal_utils.py
onetick/query_webapi/config.py
onetick/query_webapi/configuration.py
onetick/query_webapi/exception.py
onetick/query_webapi/graph_components.py
onetick/query_webapi/open_id.py
onetick/query_webapi/query.py
onetick/query_webapi/render.py
onetick/query_webapi/special_eps.py
onetick/query_webapi/symbol.py
onetick/query_webapi/utils.py
onetick/query_webapi/ep/__init__.py
onetick/query_webapi/ep/eps.py
onetick/query_webapi/plugin/__init__.py
onetick_query_webapi-20251218.0.1.dist-info/METADATA
onetick_query_webapi-20251218.0.1.dist-info/WHEEL
onetick_query_webapi-20251218.0.1.dist-info/top_level.txt
onetick_query_webapi-20251218.0.1.dist-info/zip-safe
onetick_query_webapi-20251218.0.1.dist-info/RECORD
