Metadata-Version: 2.1
Name: onetick-query-webapi
Version: 20251218.0.1
Summary: OneTick web client package
Home-page: https://www.onetick.com
Author: OneTick
Author-email: support@onetick.com
License: MIT
Platform: UNKNOWN
Classifier: Programming Language :: Python :: 3
Requires-Dist: numpy
Requires-Dist: pyarrow (>=14.0.1)
Requires-Dist: zstandard
Requires-Dist: requests (>=2.31.0)
Requires-Dist: urllib3 (>=2.1.0)
Requires-Dist: tzlocal (>=5.0)
Requires-Dist: pandas
Requires-Dist: click
Requires-Dist: graphviz
Requires-Dist: backports.zstd ; python_version < "3.14"
